<?xml version="1.0" encoding="UTF-8"?><operatorModel xmlns="http://www.ibm.com/xmlns/prod/streams/spl/operator" xmlns:cmn="http://www.ibm.com/xmlns/prod/streams/spl/common" xmlns:xsi="http://www.w3.org/2001/XMLSchema-instance" xsi:schemaLocation="http://www.ibm.com/xmlns/prod/streams/spl/operator operatorModel.xsd">
  <!--DO NOT EDIT THIS FILE - it is machine generated-->
  <javaOperatorModel>
    <!--Generated from com.ibm.streamsx.sparkmllib.tree.SparkDecisionTree in impl/java/bin/com/ibm/streamsx/sparkanalytics/SparkDecisionTree$StreamsModel.class at Sat Jun 06 12:06:52 EDT 2015-->
    <context>
      <description>This operator provides support for analysis of incoming tuple data against Apache Spark's decision tree machine learning library.</description>
      <metrics/>
      <executionSettings>
        <className>com.ibm.streamsx.sparkmllib.tree.SparkDecisionTree</className>
      </executionSettings>
      <libraryDependencies>
        <library>
          <cmn:description>Operator class library</cmn:description>
          <cmn:managedLibrary>
            <cmn:libPath>../../impl/lib/streams-sparkmllib.jar</cmn:libPath>
            <cmn:libPath>@SPARK_HOME@/lib/*</cmn:libPath>
          </cmn:managedLibrary>
        </library>
      </libraryDependencies>
    </context>
    <parameters>
    <parameter>
        <name>testDataAttr</name>
        <description/>
        <optional>false</optional>
        <expressionMode>Attribute</expressionMode>
        <type>list&lt;float64&gt;</type>
        <cardinality>1</cardinality>
      </parameter>
      <parameter>
        <name>modelPath</name>
        <description>The path containing the persisted analytic model</description>
        <optional>false</optional>
        <type>rstring</type>
        <cardinality>1</cardinality>
      </parameter>
      <parameter>
        <name>params</name>
        <description>The parameters to be passed to the spark configuration as a comma-separated list of 'key=value'</description>
        <optional>true</optional>
        <type>rstring</type>
        <cardinality>1</cardinality>
      </parameter>
      <parameter>
        <name>sparkMaster</name>
        <description>The spark master to use during the analysis. If not specified, the default value is 'local'</description>
        <optional>true</optional>
        <type>rstring</type>
        <cardinality>1</cardinality>
      </parameter>
    </parameters>
    <inputPorts>
      <inputPortSet>
        <description>This input port is required. The operator expects an attribute of type list&lt;float64&gt; that will be used as input to the decision tree algorithm.</description>
        <windowingDescription/>
        <windowingMode>NonWindowed</windowingMode>
        <windowPunctuationInputMode>Oblivious</windowPunctuationInputMode>
        <controlPort>false</controlPort>
        <cardinality>1</cardinality>
        <optional>false</optional>
      </inputPortSet>
      <inputPortSet>
        <description>This input control port is optional. The port expects a single attribute of type rstring and the value must be a string in JSON format. For example, to reload the spark model, the attribute value must be set to '{"reloadModel":true}'.</description>
        <windowingDescription/>
        <windowingMode>NonWindowed</windowingMode>
        <windowPunctuationInputMode>Oblivious</windowPunctuationInputMode>
        <controlPort>true</controlPort>
        <cardinality>1</cardinality>
        <optional>true</optional>
      </inputPortSet>
    </inputPorts>
    <outputPorts>
      <outputPortSet>
        <description>This output port is required. The operator passes through all attributes on the input port as-is to the output port. In addition, it expects an attribute called 'analysisResult' of type float64.</description>
        <windowPunctuationOutputMode>Free</windowPunctuationOutputMode>
        <cardinality>1</cardinality>
        <optional>false</optional>
      </outputPortSet>
    </outputPorts>
  </javaOperatorModel>
</operatorModel>